{
  "version": "3.0",
  "type": "category-customization-template",
  "generated": "2026-04-22T16:16:21.233022Z",
  "category": "architecture",
  "metadata": {
    "total_items": 2,
    "customizable": 0,
    "immutable": 2
  },
  "items": [
    {
      "id": "M001",
      "title": "Clean Architecture as Foundation",
      "type": "MANDATE",
      "category": "architecture",
      "criticality": "OBRIGAT\u00d3RIO",
      "customizable": false,
      "content": "All systems must implement 8-layer Clean Architecture as defined in ADR-001. The layers are:",
      "_status": "\ud83d\udd12 Immutable (core governance)"
    },
    {
      "id": "ADR-001",
      "title": "Clean Architecture 8-Layer Pattern",
      "type": "DECISION",
      "category": "architecture",
      "criticality": "OBRIGAT\u00d3RIO",
      "customizable": false,
      "content": "# ADR-001: Clean Architecture 8-Layer Pattern\n\n## Status\n- **Accepted** \u2705\n- Proposed: 2025-06-15\n- Accepted: 2025-06-20\n\n## Context\n\n**Problem**: The system needed clear separation between business logic, adaptation, and infrastructure.\n\n## Decision\n\n**Implement 8-layer Clean Architecture**:\n\n```\nLayer 8: Controllers & Interfaces (HTTP, CLI)\nLayer 7: DTOs & Serialization (Pydantic models)\nLayer 6: Adapters (Implementation of ports)\nLayer 5: Error Mapping (Domain \u2192 HTTP)\nLayer 4: Use Cases (Orchestration)\nLayer 3: Ports (Abstraction, interfaces)\nLayer 2: Domain (Business logic)\nLayer 1: Entities (Domain models)\n```\n\n## Consequences\n\n- \u2705 Consistency across all features\n- \u2705 Easy to spot violations\n- \u26a0\ufe0f More layers = more indirection\n",
      "_status": "\ud83d\udd12 Immutable (core governance)"
    }
  ]
}